tappet/__init__.py
tappet/app.py
tappet/cli.py
tappet/http_client.py
tappet/models.py
tappet/storage/__init__.py
tappet/storage/config.py
tappet/storage/paths.py
tappet/storage/requests.py
tappet/store.py
tappet/themes/default.css
tappet/utils/__init__.py
tappet/utils/clipboard.py
tappet/utils/editor.py
tappet-0.2.1.dist-info/METADATA
tappet-0.2.1.dist-info/WHEEL
tappet-0.2.1.dist-info/entry_points.txt
tappet-0.2.1.dist-info/licenses/LICENSE
tappet-0.2.1.dist-info/RECORD
